cq_centrifugal_fan/__init__.py
cq_centrifugal_fan/debug.py
cq_centrifugal_fan/errors.py
cq_centrifugal_fan/shapes.py
cq_centrifugal_fan/use_cases/__init__.py
cq_centrifugal_fan/use_cases/default.py
cq_centrifugal_fan-0.0.8.dist-info/LICENSE
cq_centrifugal_fan-0.0.8.dist-info/METADATA
cq_centrifugal_fan-0.0.8.dist-info/WHEEL
cq_centrifugal_fan-0.0.8.dist-info/top_level.txt
cq_centrifugal_fan-0.0.8.dist-info/RECORD
