Metadata-Version: 2.1
Name: cq-centrifugal-fan
Version: 0.0.8
Summary: Fully parametric centrifugal fan builder in CadQuery
Home-page: https://github.com/farnasirim/cq-centrifugal-fan
Author: farnasirim
Author-email: Mohammad Nasirifar <farnasirim@gmail.com>
Maintainer-email: Mohammad Nasirifar <farnasirim@gmail.com>
License: MIT License
Project-URL: Homepage, https://github.com/farnasirim/cq-centrifugal-fan
Project-URL: Bug Reports, https://github.com/farnasirim/cq-centrifugal-fan/issues
Project-URL: Funding, https://farnasirim.com
Project-URL: Say Thanks!, https://farnasirim.com/thanks
Project-URL: Source, https://github.com/farnasirim/cq-centrifugal-fan
Keywords: cad,cadquery
Classifier: Development Status :: 3 - Alpha
Classifier: Intended Audience :: Developers
Classifier: License :: OSI Approved :: MIT License
Classifier: Programming Language :: Python :: 3.7
Classifier: Programming Language :: Python :: 3.8
Classifier: Programming Language :: Python :: 3.9
Classifier: Programming Language :: Python :: 3.10
Classifier: Programming Language :: Python :: 3.11
Classifier: Programming Language :: Python :: 3 :: Only
Requires-Python: >=3.6
License-File: LICENSE
Requires-Dist: numpy
Requires-Dist: cadquery >=2
Requires-Dist: cqkit
Provides-Extra: dev
Requires-Dist: ocp-vscode ; extra == 'dev'
Requires-Dist: jupyter-cadquery ; extra == 'dev'
